<?xml version="1.0" encoding="UTF-8"?>
<Recipe>
    <image size="large" content="apple frangipane tart and cream"/>
    <quote>The sweet frangipane filling with almonds is a lovely addition and really brings these little tarts to whole new flavour level.</quote>
        <quoteauthor>Shibani</quoteauthor>
            <quoteauthorcompany>Pearlsofeast</quoteauthorcompany>
    <title>Apple Frangipane Tart</title>
        <ingredients>
            <item>almond meal</item>
                <quantity>3/4</quantity>            
                <unitofmeasurement>cup</unitofmeasurement>
            <item>plain flour</item>
                <quantity>1 1/2</quantity>
                <unitofmeasurement>tablespoon</unitofmeasurement>
            <item>sugar</item>
                <quantity>1/4</quantity>
                <unitofmeasurement>cup</unitofmeasurement>
            <item>unsalted butter</item>
                <quantity>50</quantity>
                <unitofmeasurement>grams</unitofmeasurement>
            <item>large egg</item>
                <quantity>1</quantity>
            <item>vanilla extract</item>
                <quantity>1/2</quantity>
                <unitofmeasurement>teaspoon</unitofmeasurement>
            <item>puff pastry</item>
                <quantity>2</quantity>
                <unitofmeasurement>sheets</unitofmeasurement>
            <item>apples</item>
                <itemtype>sliced</itemtype>
                <quantity>2 or 3</quantity>
            <item>melted butter and sugar mixture</item>
                <item>butter</item>
                    <itemtype>melted</itemtype>
                <item>sugar</item>    
                    <quantity>1</quantity>
                    <unitofmeasurement>tablespoon</unitofmeasurement>
        </ingredients>      
     <preparation>
         <step>Preheat the oven to 200&#176;C. Place the pastry on a lined oven tray to thaw. Cut 1 sheet into 4 squares and prick all over with a fork to stop it puffing up too much and other one I choose to have it as a round circle.</step>
         <step>For frangipane filling, cream the sugar and butter together until light. Add egg and mix to combine. Finally add the almonds, extract to combine.</step>
         <step>Spread the frangipane evenly into the puff pastry sheets leaving 1cm from the edges. Arrange the apples slices in a pretty petal pattern.</step>
         <step>Brush with melted butter and sprinkle with the extra sugar. Bake for about 20-25 minutes till the pastry is puffed and golden around the edges. Drizzle with honey and serve with dollup of double cream.</step>               
     </preparation>          
</Recipe>
